dexcontrol/__init__.py
dexcontrol/robot.py
dexcontrol/apps/dualsense_teleop_base.py
dexcontrol/comm/__init__.py
dexcontrol/comm/rtc.py
dexcontrol/comm/subscribers.py
dexcontrol/config/__init__.py
dexcontrol/config/vega.py
dexcontrol/config/core/__init__.py
dexcontrol/config/core/arm.py
dexcontrol/config/core/chassis.py
dexcontrol/config/core/hand.py
dexcontrol/config/core/head.py
dexcontrol/config/core/misc.py
dexcontrol/config/core/torso.py
dexcontrol/config/sensors/__init__.py
dexcontrol/config/sensors/vega_sensors.py
dexcontrol/config/sensors/cameras/__init__.py
dexcontrol/config/sensors/cameras/rgb_camera.py
dexcontrol/config/sensors/cameras/zed_camera.py
dexcontrol/config/sensors/imu/__init__.py
dexcontrol/config/sensors/imu/chassis_imu.py
dexcontrol/config/sensors/imu/zed_imu.py
dexcontrol/config/sensors/lidar/__init__.py
dexcontrol/config/sensors/lidar/rplidar.py
dexcontrol/config/sensors/ultrasonic/__init__.py
dexcontrol/config/sensors/ultrasonic/ultrasonic.py
dexcontrol/core/__init__.py
dexcontrol/core/arm.py
dexcontrol/core/chassis.py
dexcontrol/core/component.py
dexcontrol/core/hand.py
dexcontrol/core/head.py
dexcontrol/core/misc.py
dexcontrol/core/robot_query_interface.py
dexcontrol/core/torso.py
dexcontrol/sensors/__init__.py
dexcontrol/sensors/manager.py
dexcontrol/sensors/ultrasonic.py
dexcontrol/sensors/camera/__init__.py
dexcontrol/sensors/camera/base_camera.py
dexcontrol/sensors/camera/rgb_camera.py
dexcontrol/sensors/camera/zed_camera.py
dexcontrol/sensors/imu/__init__.py
dexcontrol/sensors/imu/chassis_imu.py
dexcontrol/sensors/imu/zed_imu.py
dexcontrol/sensors/lidar/__init__.py
dexcontrol/sensors/lidar/rplidar.py
dexcontrol/utils/__init__.py
dexcontrol/utils/comm_helper.py
dexcontrol/utils/constants.py
dexcontrol/utils/error_code.py
dexcontrol/utils/io_utils.py
dexcontrol/utils/os_utils.py
dexcontrol/utils/pb_utils.py
dexcontrol/utils/timer.py
dexcontrol/utils/trajectory_utils.py
dexcontrol/utils/viz_utils.py
dexcontrol-0.3.4.dist-info/METADATA
dexcontrol-0.3.4.dist-info/WHEEL
dexcontrol-0.3.4.dist-info/licenses/LICENSE
dexcontrol-0.3.4.dist-info/RECORD
