Metadata-Version: 2.4
Name: dexcontrol
Version: 0.3.4
Summary: A Python library of Sensing and Control for Dexmate's Robot
Project-URL: Repository, https://github.com/dexmate-ai/dexcontrol
Author-email: Dexmate <contact@dexmate.ai>
License: GNU AFFERO GENERAL PUBLIC LICENSE
License-File: LICENSE
Keywords: control,learning,python,robot
Classifier: Framework :: Robot Framework :: Library
Classifier: Intended Audience :: Developers
Classifier: Intended Audience :: Science/Research
Classifier: Operating System :: OS Independent
Classifier: Programming Language :: Python :: 3
Classifier: Programming Language :: Python :: 3.10
Classifier: Programming Language :: Python :: 3.11
Classifier: Programming Language :: Python :: 3.12
Classifier: Programming Language :: Python :: 3.13
Classifier: Typing :: Typed
Requires-Python: <3.14,>=3.10
Requires-Dist: aiortc
Requires-Dist: dexcomm>=0.1.18
Requires-Dist: eclipse-zenoh>=1.2.0
Requires-Dist: hydra-core==1.3.2
Requires-Dist: jaxtyping>=0.2.38
Requires-Dist: loguru>=0.7.3
Requires-Dist: numpy>=1.26.4
Requires-Dist: opencv-python>=4.11.0
Requires-Dist: rich
Requires-Dist: uvloop>=0.17.0; sys_platform != 'win32'
Requires-Dist: websockets
Provides-Extra: dev
Requires-Dist: isort>=5.12.0; extra == 'dev'
Requires-Dist: pre-commit; extra == 'dev'
Requires-Dist: pyright; extra == 'dev'
Requires-Dist: pytest-cov>=4.1.0; extra == 'dev'
Requires-Dist: pytest>=7.4.0; extra == 'dev'
Requires-Dist: ruff; extra == 'dev'
Provides-Extra: docs
Requires-Dist: furo>=2023.09.10; extra == 'docs'
Requires-Dist: markitdown[all]>=0.1.0; extra == 'docs'
Requires-Dist: myst-parser>=2.0.0; extra == 'docs'
Requires-Dist: sphinx-autodoc-typehints>=1.24.0; extra == 'docs'
Requires-Dist: sphinx-rtd-theme>=1.3.0; extra == 'docs'
Requires-Dist: sphinx>=7.0.0; extra == 'docs'
Provides-Extra: example
Requires-Dist: dexmotion>=0.2.1; extra == 'example'
Requires-Dist: dualsense-controller>=0.3.1; extra == 'example'
Requires-Dist: matplotlib>=3.8.0; extra == 'example'
Requires-Dist: pytransform3d==3.13.0; extra == 'example'
Requires-Dist: scipy>=1.16.1; extra == 'example'
Requires-Dist: tyro; extra == 'example'
